wenlan_video/__init__.py
wenlan_video/dataset/__init__.py
wenlan_video/dataset/dataset.py
wenlan_video/models/__init__.py
wenlan_video/models/bert.py
wenlan_video/models/fakeTransformer.py
wenlan_video/models/vl_model.py
wenlan_video/utils/__init__.py
wenlan_video/utils/config.py
wenlan_video/utils/load.py
wenlan_video_public-1.0.2.dist-info/LICENSE
wenlan_video_public-1.0.2.dist-info/METADATA
wenlan_video_public-1.0.2.dist-info/WHEEL
wenlan_video_public-1.0.2.dist-info/top_level.txt
wenlan_video_public-1.0.2.dist-info/RECORD
