Metadata-Version: 2.1
Name: wenlan-video-public
Version: 1.0.2
Summary: Wenlan - Large scale cross-modal pre-training model
Home-page: https://github.com/rucmlcv/Wenlan-Video-Public
Author: Haoyu Lu
Author-email: lhy1998@ruc.edu.cn
License: MIT Licence
Keywords: pip,wenlan
Platform: any
Classifier: Programming Language :: Python :: 3
Classifier: License :: OSI Approved :: MIT License
Classifier: Operating System :: OS Independent
License-File: LICENSE
Requires-Dist: numpy
